mcp_automl/__init__.py
mcp_automl/__main__.py
mcp_automl/server.py
mcp_automl-0.1.0.dist-info/METADATA
mcp_automl-0.1.0.dist-info/WHEEL
mcp_automl-0.1.0.dist-info/entry_points.txt
mcp_automl-0.1.0.dist-info/RECORD
