Metadata-Version: 2.4
Name: mcp-automl
Version: 0.1.0
Summary: MCP server for end-to-end machine learning
Requires-Python: >=3.11
Requires-Dist: duckdb>=1.4.3
Requires-Dist: joblib<1.4
Requires-Dist: mcp>=1.21.2
Requires-Dist: pandas<2.2.0
Requires-Dist: pycaret>=3.0.0
Requires-Dist: scikit-learn<1.4
Requires-Dist: tabulate>=0.9.0
